<?xml version="1.0" encoding="UTF-8"?>
<suite name="Suite">
  <test name="Test">
    <classes>
      <class name="testNG.Login_Page"/>
      <methods>
      <include name="openUrl"/>
      <include name="login"/>
      <include name="testFunctionality"/>
      </methods>
    </classes>
  </test> 
  <test name="Test1">
    <classes>
      <class name="testNG.Login_Page"/>
      <methods>
      <include name="openUrl"/>
      <include name="login"/>
      <include name="testFunctionality2"/>
      </methods>
    </classes>
  </test> <!-- Test -->
</suite> 
